pybarb/__init__.py
pybarb/pybarb.py
pybarb-0.5.2.dist-info/METADATA
pybarb-0.5.2.dist-info/WHEEL
pybarb-0.5.2.dist-info/top_level.txt
pybarb-0.5.2.dist-info/RECORD
