Metadata-Version: 2.1
Name: pybarb
Version: 0.5.2
Summary: A package to interact with the BARB API
Home-page: https://github.com/coppeliaMLA/barb_api
Author: Simon Raper
Author-email: info@barb.co.uk
Requires-Dist: pandas
Requires-Dist: sqlalchemy
Requires-Dist: plotly
Requires-Dist: requests
